cogmyra/__init__.py
cogmyra/cli.py
cogmyra/core.py
cogmyra/memory.py
cogmyra-0.3.5.dist-info/METADATA
cogmyra-0.3.5.dist-info/WHEEL
cogmyra-0.3.5.dist-info/entry_points.txt
cogmyra-0.3.5.dist-info/RECORD
